{"prime": 11117, "nodes": 927, "minpoly": "x^2 + 11116*x + 3", "spine": 33, "undirected": false, "ell": {"2": {"diameter": 13, "conjugate_isogenous_pairs": 19, "eigenvalues": [2.8133606365855126, -2.826936929182119]}, "3": {"diameter": 10, "conjugate_isogenous_pairs": 75, "eigenvalues": [3.4399098354876267, -3.4441418388768907]}, "5": {"diameter": 7, "conjugate_isogenous_pairs": 39, "eigenvalues": [4.460858144335904, -4.460969688132215]}, "7": {"diameter": 5, "conjugate_isogenous_pairs": 94, "eigenvalues": [5.202868016480597, -5.263608103499184]}, "11": {"diameter": 5, "conjugate_isogenous_pairs": 71, "eigenvalues": [6.523136008010412, -6.6219950888817785]}}}