{"prime": 25219, "nodes": 2102, "minpoly": "x^2 + 25210*x + 2", "spine": 86, "undirected": false, "ell": {"2": {"diameter": 16, "conjugate_isogenous_pairs": 53, "eigenvalues": [2.8209661890794413, -2.824975803835155]}, "3": {"diameter": 10, "conjugate_isogenous_pairs": 36, "eigenvalues": [3.4507171246712556, -3.458618917028253]}, "5": {"diameter": 7, "conjugate_isogenous_pairs": 118, "eigenvalues": [4.438770145526529, -4.460658197623527]}, "7": {"diameter": 6, "conjugate_isogenous_pairs": 26, "eigenvalues": [5.269439413534275, -5.284289617829197]}, "11": {"diameter": 5, "conjugate_isogenous_pairs": 143, "eigenvalues": [6.54976760457035, -6.5989701587328815]}}}