{"prime": 3833, "nodes": 320, "minpoly": "x^2 + 3827*x + 3", "spine": 22, "undirected": false, "ell": {"2": {"diameter": 11, "conjugate_isogenous_pairs": 16, "eigenvalues": [2.795011741210767, -2.774810109723749]}, "3": {"diameter": 8, "conjugate_isogenous_pairs": 23, "eigenvalues": [3.398211375855109, -3.435944728202735]}, "5": {"diameter": 5, "conjugate_isogenous_pairs": 15, "eigenvalues": [4.433008818558139, -4.467315459946617]}, "7": {"diameter": 5, "conjugate_isogenous_pairs": 86, "eigenvalues": [5.215533842337799, -5.252700474421624]}, "11": {"diameter": 4, "conjugate_isogenous_pairs": 21, "eigenvalues": [6.350879642962077, -6.444529734240529]}}}