{"prime": 4391, "nodes": 367, "minpoly": "x^2 + 4388*x + 14", "spine": 79, "undirected": false, "ell": {"2": {"diameter": 12, "conjugate_isogenous_pairs": 6, "eigenvalues": [2.787570533816152, -2.7933048475346807]}, "3": {"diameter": 9, "conjugate_isogenous_pairs": 21, "eigenvalues": [3.4506576821211605, -3.3873192977889217]}, "5": {"diameter": 6, "conjugate_isogenous_pairs": 23, "eigenvalues": [4.433240159381709, -4.451946655418931]}, "7": {"diameter": 5, "conjugate_isogenous_pairs": 25, "eigenvalues": [5.238321701345523, -5.240369592398176]}, "11": {"diameter": 4, "conjugate_isogenous_pairs": 23, "eigenvalues": [6.526760935081348, -6.544191790091836]}}}