{"prime": 29339, "nodes": 2446, "minpoly": "x^2 + 29333*x + 2", "spine": 122, "undirected": false, "ell": {"2": {"diameter": 15, "conjugate_isogenous_pairs": 20, "eigenvalues": [2.8262686790182916, -2.827475296616873]}, "3": {"diameter": 10, "conjugate_isogenous_pairs": 45, "eigenvalues": [3.4361500784973678, -3.450547603391564]}, "5": {"diameter": 7, "conjugate_isogenous_pairs": 141, "eigenvalues": [4.453366079151955, -4.452179152189662]}, "7": {"diameter": 6, "conjugate_isogenous_pairs": 103, "eigenvalues": [5.283593193667623, -5.264802487840703]}, "11": {"diameter": 5, "conjugate_isogenous_pairs": 80, "eigenvalues": [6.585341683431576, -6.526926886446704]}}}